[
  {
    "n": 1,
    "chapter_id": "1.1",
    "chapter_name": "数と式",
    "subject": "数I",
    "audience": "文理共通",
    "difficulty": 1,
    "t_number": 5,
    "question_page": 2,
    "answer_page": 37,
    "answer_end_page": 38
  },
  {
    "n": 2,
    "chapter_id": "1.1",
    "chapter_name": "数と式",
    "subject": "数I",
    "audience": "文理共通",
    "difficulty": 1,
    "t_number": 15,
    "question_page": 2,
    "answer_page": 39,
    "answer_end_page": 39
  },
  {
    "n": 3,
    "chapter_id": "1.1",
    "chapter_name": "数と式",
    "subject": "数I",
    "audience": "文理共通",
    "difficulty": 1,
    "t_number": 64,
    "question_page": 2,
    "answer_page": 40,
    "answer_end_page": 41
  },
  {
    "n": 4,
    "chapter_id": "1.1",
    "chapter_name": "数と式",
    "subject": "数I",
    "audience": "文理共通",
    "difficulty": 1,
    "t_number": 100,
    "question_page": 2,
    "answer_page": 42,
    "answer_end_page": 43
  },
  {
    "n": 5,
    "chapter_id": "1.1",
    "chapter_name": "数と式",
    "subject": "数I",
    "audience": "文理共通",
    "difficulty": 1,
    "t_number": 113,
    "question_page": 2,
    "answer_page": 44,
    "answer_end_page": 45
  },
  {
    "n": 6,
    "chapter_id": "1.1",
    "chapter_name": "数と式",
    "subject": "数I",
    "audience": "文理共通",
    "difficulty": 1,
    "t_number": 123,
    "question_page": 3,
    "answer_page": 46,
    "answer_end_page": 46
  },
  {
    "n": 7,
    "chapter_id": "1.1",
    "chapter_name": "数と式",
    "subject": "数I",
    "audience": "文理共通",
    "difficulty": 1,
    "t_number": 124,
    "question_page": 3,
    "answer_page": 47,
    "answer_end_page": 48
  },
  {
    "n": 8,
    "chapter_id": "1.1",
    "chapter_name": "数と式",
    "subject": "数I",
    "audience": "文理共通",
    "difficulty": 1,
    "t_number": 138,
    "question_page": 3,
    "answer_page": 49,
    "answer_end_page": 50
  },
  {
    "n": 9,
    "chapter_id": "1.1",
    "chapter_name": "数と式",
    "subject": "数I",
    "audience": "文理共通",
    "difficulty": 1,
    "t_number": 152,
    "question_page": 3,
    "answer_page": 51,
    "answer_end_page": 52
  },
  {
    "n": 10,
    "chapter_id": "1.1",
    "chapter_name": "数と式",
    "subject": "数I",
    "audience": "文理共通",
    "difficulty": 1,
    "t_number": 201,
    "question_page": 3,
    "answer_page": 53,
    "answer_end_page": 54
  },
  {
    "n": 11,
    "chapter_id": "1.1",
    "chapter_name": "数と式",
    "subject": "数I",
    "audience": "文理共通",
    "difficulty": 1,
    "t_number": 238,
    "question_page": 3,
    "answer_page": 55,
    "answer_end_page": 56
  },
  {
    "n": 12,
    "chapter_id": "1.1",
    "chapter_name": "数と式",
    "subject": "数A",
    "audience": "文理共通",
    "difficulty": 1,
    "t_number": 92,
    "question_page": 3,
    "answer_page": 57,
    "answer_end_page": 58
  },
  {
    "n": 13,
    "chapter_id": "1.1",
    "chapter_name": "数と式",
    "subject": "数A",
    "audience": "文理共通",
    "difficulty": 1,
    "t_number": 207,
    "question_page": 4,
    "answer_page": 59,
    "answer_end_page": 59
  },
  {
    "n": 14,
    "chapter_id": "1.1",
    "chapter_name": "数と式",
    "subject": "数II",
    "audience": "文理共通",
    "difficulty": 1,
    "t_number": 44,
    "question_page": 4,
    "answer_page": 60,
    "answer_end_page": 61
  },
  {
    "n": 15,
    "chapter_id": "1.1",
    "chapter_name": "数と式",
    "subject": "数II",
    "audience": "文理共通",
    "difficulty": 1,
    "t_number": 53,
    "question_page": 4,
    "answer_page": 62,
    "answer_end_page": 63
  },
  {
    "n": 16,
    "chapter_id": "1.1",
    "chapter_name": "数と式",
    "subject": "数II",
    "audience": "文理共通",
    "difficulty": 1,
    "t_number": 87,
    "question_page": 4,
    "answer_page": 64,
    "answer_end_page": 65
  },
  {
    "n": 17,
    "chapter_id": "1.1",
    "chapter_name": "数と式",
    "subject": "数II",
    "audience": "文理共通",
    "difficulty": 1,
    "t_number": 165,
    "question_page": 4,
    "answer_page": 66,
    "answer_end_page": 67
  },
  {
    "n": 18,
    "chapter_id": "1.1",
    "chapter_name": "数と式",
    "subject": "数II",
    "audience": "文理共通",
    "difficulty": 1,
    "t_number": 183,
    "question_page": 4,
    "answer_page": 68,
    "answer_end_page": 68
  },
  {
    "n": 19,
    "chapter_id": "1.1",
    "chapter_name": "数と式",
    "subject": "数II",
    "audience": "文理共通",
    "difficulty": 1,
    "t_number": 200,
    "question_page": 4,
    "answer_page": 69,
    "answer_end_page": 70
  },
  {
    "n": 20,
    "chapter_id": "1.1",
    "chapter_name": "数と式",
    "subject": "数II",
    "audience": "文理共通",
    "difficulty": 1,
    "t_number": 202,
    "question_page": 5,
    "answer_page": 71,
    "answer_end_page": 72
  },
  {
    "n": 21,
    "chapter_id": "1.1",
    "chapter_name": "数と式",
    "subject": "数II",
    "audience": "文理共通",
    "difficulty": 2,
    "t_number": 28,
    "question_page": 5,
    "answer_page": 73,
    "answer_end_page": 74
  },
  {
    "n": 22,
    "chapter_id": "1.1",
    "chapter_name": "数と式",
    "subject": "数II",
    "audience": "文理共通",
    "difficulty": 2,
    "t_number": 71,
    "question_page": 5,
    "answer_page": 75,
    "answer_end_page": 76
  },
  {
    "n": 23,
    "chapter_id": "1.1",
    "chapter_name": "数と式",
    "subject": "数II",
    "audience": "文理共通",
    "difficulty": 2,
    "t_number": 130,
    "question_page": 5,
    "answer_page": 77,
    "answer_end_page": 78
  },
  {
    "n": 24,
    "chapter_id": "1.1",
    "chapter_name": "数と式",
    "subject": "数II",
    "audience": "理系のみ",
    "difficulty": 2,
    "t_number": 9,
    "question_page": 5,
    "answer_page": 79,
    "answer_end_page": 79
  },
  {
    "n": 25,
    "chapter_id": "1.2",
    "chapter_name": "方程式・不等式",
    "subject": "数I",
    "audience": "文理共通",
    "difficulty": 1,
    "t_number": 51,
    "question_page": 5,
    "answer_page": 80,
    "answer_end_page": 81
  },
  {
    "n": 26,
    "chapter_id": "1.2",
    "chapter_name": "方程式・不等式",
    "subject": "数I",
    "audience": "文理共通",
    "difficulty": 1,
    "t_number": 69,
    "question_page": 5,
    "answer_page": 82,
    "answer_end_page": 83
  },
  {
    "n": 27,
    "chapter_id": "1.2",
    "chapter_name": "方程式・不等式",
    "subject": "数I",
    "audience": "文理共通",
    "difficulty": 1,
    "t_number": 94,
    "question_page": 6,
    "answer_page": 84,
    "answer_end_page": 84
  },
  {
    "n": 28,
    "chapter_id": "1.2",
    "chapter_name": "方程式・不等式",
    "subject": "数I",
    "audience": "文理共通",
    "difficulty": 1,
    "t_number": 128,
    "question_page": 6,
    "answer_page": 85,
    "answer_end_page": 86
  },
  {
    "n": 29,
    "chapter_id": "1.2",
    "chapter_name": "方程式・不等式",
    "subject": "数I",
    "audience": "文理共通",
    "difficulty": 1,
    "t_number": 204,
    "question_page": 6,
    "answer_page": 87,
    "answer_end_page": 88
  },
  {
    "n": 30,
    "chapter_id": "1.2",
    "chapter_name": "方程式・不等式",
    "subject": "数I",
    "audience": "文理共通",
    "difficulty": 2,
    "t_number": 134,
    "question_page": 6,
    "answer_page": 89,
    "answer_end_page": 90
  },
  {
    "n": 31,
    "chapter_id": "1.2",
    "chapter_name": "方程式・不等式",
    "subject": "数I",
    "audience": "文理共通",
    "difficulty": 2,
    "t_number": 181,
    "question_page": 6,
    "answer_page": 91,
    "answer_end_page": 92
  },
  {
    "n": 32,
    "chapter_id": "1.2",
    "chapter_name": "方程式・不等式",
    "subject": "数I",
    "audience": "文理共通",
    "difficulty": 2,
    "t_number": 232,
    "question_page": 6,
    "answer_page": 93,
    "answer_end_page": 94
  },
  {
    "n": 33,
    "chapter_id": "1.2",
    "chapter_name": "方程式・不等式",
    "subject": "数I",
    "audience": "文理共通",
    "difficulty": 2,
    "t_number": 233,
    "question_page": 6,
    "answer_page": 95,
    "answer_end_page": 96
  },
  {
    "n": 34,
    "chapter_id": "1.2",
    "chapter_name": "方程式・不等式",
    "subject": "数I",
    "audience": "文理共通",
    "difficulty": 2,
    "t_number": 234,
    "question_page": 6,
    "answer_page": 97,
    "answer_end_page": 98
  },
  {
    "n": 35,
    "chapter_id": "1.2",
    "chapter_name": "方程式・不等式",
    "subject": "数I",
    "audience": "文理共通",
    "difficulty": 2,
    "t_number": 235,
    "question_page": 7,
    "answer_page": 99,
    "answer_end_page": 100
  },
  {
    "n": 36,
    "chapter_id": "1.2",
    "chapter_name": "方程式・不等式",
    "subject": "数I",
    "audience": "文理共通",
    "difficulty": 2,
    "t_number": 236,
    "question_page": 7,
    "answer_page": 101,
    "answer_end_page": 102
  },
  {
    "n": 37,
    "chapter_id": "1.2",
    "chapter_name": "方程式・不等式",
    "subject": "数II",
    "audience": "文理共通",
    "difficulty": 1,
    "t_number": 22,
    "question_page": 7,
    "answer_page": 103,
    "answer_end_page": 103
  },
  {
    "n": 38,
    "chapter_id": "1.2",
    "chapter_name": "方程式・不等式",
    "subject": "数II",
    "audience": "文理共通",
    "difficulty": 1,
    "t_number": 74,
    "question_page": 7,
    "answer_page": 104,
    "answer_end_page": 105
  },
  {
    "n": 39,
    "chapter_id": "1.2",
    "chapter_name": "方程式・不等式",
    "subject": "数II",
    "audience": "文理共通",
    "difficulty": 1,
    "t_number": 250,
    "question_page": 7,
    "answer_page": 106,
    "answer_end_page": 107
  },
  {
    "n": 40,
    "chapter_id": "1.2",
    "chapter_name": "方程式・不等式",
    "subject": "数II",
    "audience": "文理共通",
    "difficulty": 2,
    "t_number": 66,
    "question_page": 7,
    "answer_page": 108,
    "answer_end_page": 109
  },
  {
    "n": 41,
    "chapter_id": "1.2",
    "chapter_name": "方程式・不等式",
    "subject": "数II",
    "audience": "文理共通",
    "difficulty": 2,
    "t_number": 122,
    "question_page": 7,
    "answer_page": 110,
    "answer_end_page": 111
  },
  {
    "n": 42,
    "chapter_id": "1.2",
    "chapter_name": "方程式・不等式",
    "subject": "数II",
    "audience": "文理共通",
    "difficulty": 3,
    "t_number": 23,
    "question_page": 7,
    "answer_page": 112,
    "answer_end_page": 112
  },
  {
    "n": 43,
    "chapter_id": "1.2",
    "chapter_name": "方程式・不等式",
    "subject": "数II",
    "audience": "文理共通",
    "difficulty": 3,
    "t_number": 36,
    "question_page": 8,
    "answer_page": 113,
    "answer_end_page": 113
  },
  {
    "n": 44,
    "chapter_id": "1.2",
    "chapter_name": "方程式・不等式",
    "subject": "数II",
    "audience": "文理共通",
    "difficulty": 3,
    "t_number": 95,
    "question_page": 8,
    "answer_page": 114,
    "answer_end_page": 115
  },
  {
    "n": 45,
    "chapter_id": "1.2",
    "chapter_name": "方程式・不等式",
    "subject": "数II",
    "audience": "文理共通",
    "difficulty": 3,
    "t_number": 102,
    "question_page": 8,
    "answer_page": 116,
    "answer_end_page": 117
  },
  {
    "n": 46,
    "chapter_id": "1.2",
    "chapter_name": "方程式・不等式",
    "subject": "数B",
    "audience": "文理共通",
    "difficulty": 1,
    "t_number": 145,
    "question_page": 8,
    "answer_page": 118,
    "answer_end_page": 119
  },
  {
    "n": 47,
    "chapter_id": "1.2",
    "chapter_name": "方程式・不等式",
    "subject": "数III",
    "audience": "理系のみ",
    "difficulty": 1,
    "t_number": 6,
    "question_page": 8,
    "answer_page": 120,
    "answer_end_page": 121
  },
  {
    "n": 48,
    "chapter_id": "1.2",
    "chapter_name": "方程式・不等式",
    "subject": "数III",
    "audience": "理系のみ",
    "difficulty": 3,
    "t_number": 45,
    "question_page": 8,
    "answer_page": 122,
    "answer_end_page": 123
  },
  {
    "n": 49,
    "chapter_id": "1.3",
    "chapter_name": "2次関数・3次関数・いろいろな関数",
    "subject": "数I",
    "audience": "文理共通",
    "difficulty": 1,
    "t_number": 26,
    "question_page": 8,
    "answer_page": 124,
    "answer_end_page": 125
  },
  {
    "n": 50,
    "chapter_id": "1.3",
    "chapter_name": "2次関数・3次関数・いろいろな関数",
    "subject": "数I",
    "audience": "文理共通",
    "difficulty": 1,
    "t_number": 31,
    "question_page": 9,
    "answer_page": 126,
    "answer_end_page": 128
  },
  {
    "n": 51,
    "chapter_id": "1.3",
    "chapter_name": "2次関数・3次関数・いろいろな関数",
    "subject": "数I",
    "audience": "文理共通",
    "difficulty": 1,
    "t_number": 33,
    "question_page": 9,
    "answer_page": 129,
    "answer_end_page": 130
  },
  {
    "n": 52,
    "chapter_id": "1.3",
    "chapter_name": "2次関数・3次関数・いろいろな関数",
    "subject": "数I",
    "audience": "文理共通",
    "difficulty": 1,
    "t_number": 47,
    "question_page": 9,
    "answer_page": 131,
    "answer_end_page": 133
  },
  {
    "n": 53,
    "chapter_id": "1.3",
    "chapter_name": "2次関数・3次関数・いろいろな関数",
    "subject": "数I",
    "audience": "文理共通",
    "difficulty": 1,
    "t_number": 81,
    "question_page": 9,
    "answer_page": 134,
    "answer_end_page": 135
  },
  {
    "n": 54,
    "chapter_id": "1.3",
    "chapter_name": "2次関数・3次関数・いろいろな関数",
    "subject": "数I",
    "audience": "文理共通",
    "difficulty": 1,
    "t_number": 133,
    "question_page": 9,
    "answer_page": 136,
    "answer_end_page": 137
  },
  {
    "n": 55,
    "chapter_id": "1.3",
    "chapter_name": "2次関数・3次関数・いろいろな関数",
    "subject": "数I",
    "audience": "文理共通",
    "difficulty": 2,
    "t_number": 243,
    "question_page": 9,
    "answer_page": 138,
    "answer_end_page": 139
  },
  {
    "n": 56,
    "chapter_id": "1.3",
    "chapter_name": "2次関数・3次関数・いろいろな関数",
    "subject": "数II",
    "audience": "文理共通",
    "difficulty": 1,
    "t_number": 80,
    "question_page": 9,
    "answer_page": 140,
    "answer_end_page": 141
  },
  {
    "n": 57,
    "chapter_id": "1.3",
    "chapter_name": "2次関数・3次関数・いろいろな関数",
    "subject": "数II",
    "audience": "文理共通",
    "difficulty": 1,
    "t_number": 171,
    "question_page": 10,
    "answer_page": 142,
    "answer_end_page": 143
  },
  {
    "n": 58,
    "chapter_id": "1.3",
    "chapter_name": "2次関数・3次関数・いろいろな関数",
    "subject": "数II",
    "audience": "文理共通",
    "difficulty": 1,
    "t_number": 172,
    "question_page": 10,
    "answer_page": 144,
    "answer_end_page": 145
  },
  {
    "n": 59,
    "chapter_id": "1.3",
    "chapter_name": "2次関数・3次関数・いろいろな関数",
    "subject": "数II",
    "audience": "文理共通",
    "difficulty": 1,
    "t_number": 178,
    "question_page": 10,
    "answer_page": 146,
    "answer_end_page": 146
  },
  {
    "n": 60,
    "chapter_id": "1.3",
    "chapter_name": "2次関数・3次関数・いろいろな関数",
    "subject": "数II",
    "audience": "文理共通",
    "difficulty": 2,
    "t_number": 35,
    "question_page": 10,
    "answer_page": 147,
    "answer_end_page": 148
  },
  {
    "n": 61,
    "chapter_id": "1.3",
    "chapter_name": "2次関数・3次関数・いろいろな関数",
    "subject": "数II",
    "audience": "文理共通",
    "difficulty": 2,
    "t_number": 58,
    "question_page": 10,
    "answer_page": 149,
    "answer_end_page": 150
  },
  {
    "n": 62,
    "chapter_id": "1.3",
    "chapter_name": "2次関数・3次関数・いろいろな関数",
    "subject": "数II",
    "audience": "文理共通",
    "difficulty": 2,
    "t_number": 76,
    "question_page": 10,
    "answer_page": 151,
    "answer_end_page": 152
  },
  {
    "n": 63,
    "chapter_id": "1.3",
    "chapter_name": "2次関数・3次関数・いろいろな関数",
    "subject": "数II",
    "audience": "文理共通",
    "difficulty": 2,
    "t_number": 167,
    "question_page": 10,
    "answer_page": 153,
    "answer_end_page": 154
  },
  {
    "n": 64,
    "chapter_id": "1.3",
    "chapter_name": "2次関数・3次関数・いろいろな関数",
    "subject": "数II",
    "audience": "文理共通",
    "difficulty": 2,
    "t_number": 196,
    "question_page": 10,
    "answer_page": 155,
    "answer_end_page": 156
  },
  {
    "n": 65,
    "chapter_id": "1.3",
    "chapter_name": "2次関数・3次関数・いろいろな関数",
    "subject": "数III",
    "audience": "理系のみ",
    "difficulty": 1,
    "t_number": 228,
    "question_page": 11,
    "answer_page": 157,
    "answer_end_page": 158
  },
  {
    "n": 66,
    "chapter_id": "1.4",
    "chapter_name": "平面図形・空間図形",
    "subject": "数I",
    "audience": "文理共通",
    "difficulty": 1,
    "t_number": 60,
    "question_page": 11,
    "answer_page": 159,
    "answer_end_page": 160
  },
  {
    "n": 67,
    "chapter_id": "1.4",
    "chapter_name": "平面図形・空間図形",
    "subject": "数I",
    "audience": "文理共通",
    "difficulty": 1,
    "t_number": 159,
    "question_page": 11,
    "answer_page": 161,
    "answer_end_page": 161
  },
  {
    "n": 68,
    "chapter_id": "1.4",
    "chapter_name": "平面図形・空間図形",
    "subject": "数I",
    "audience": "文理共通",
    "difficulty": 1,
    "t_number": 197,
    "question_page": 11,
    "answer_page": 162,
    "answer_end_page": 163
  },
  {
    "n": 69,
    "chapter_id": "1.4",
    "chapter_name": "平面図形・空間図形",
    "subject": "数I",
    "audience": "文理共通",
    "difficulty": 2,
    "t_number": 175,
    "question_page": 11,
    "answer_page": 164,
    "answer_end_page": 165
  },
  {
    "n": 70,
    "chapter_id": "1.4",
    "chapter_name": "平面図形・空間図形",
    "subject": "数A",
    "audience": "文理共通",
    "difficulty": 1,
    "t_number": 42,
    "question_page": 11,
    "answer_page": 166,
    "answer_end_page": 168
  },
  {
    "n": 71,
    "chapter_id": "1.4",
    "chapter_name": "平面図形・空間図形",
    "subject": "数A",
    "audience": "文理共通",
    "difficulty": 2,
    "t_number": 14,
    "question_page": 11,
    "answer_page": 169,
    "answer_end_page": 170
  },
  {
    "n": 72,
    "chapter_id": "1.4",
    "chapter_name": "平面図形・空間図形",
    "subject": "数A",
    "audience": "文理共通",
    "difficulty": 2,
    "t_number": 37,
    "question_page": 12,
    "answer_page": 171,
    "answer_end_page": 172
  },
  {
    "n": 73,
    "chapter_id": "1.4",
    "chapter_name": "平面図形・空間図形",
    "subject": "数A",
    "audience": "文理共通",
    "difficulty": 2,
    "t_number": 41,
    "question_page": 12,
    "answer_page": 173,
    "answer_end_page": 174
  },
  {
    "n": 74,
    "chapter_id": "1.4",
    "chapter_name": "平面図形・空間図形",
    "subject": "数A",
    "audience": "文理共通",
    "difficulty": 2,
    "t_number": 72,
    "question_page": 12,
    "answer_page": 175,
    "answer_end_page": 176
  },
  {
    "n": 75,
    "chapter_id": "1.4",
    "chapter_name": "平面図形・空間図形",
    "subject": "数A",
    "audience": "文理共通",
    "difficulty": 2,
    "t_number": 136,
    "question_page": 12,
    "answer_page": 177,
    "answer_end_page": 179
  },
  {
    "n": 76,
    "chapter_id": "1.4",
    "chapter_name": "平面図形・空間図形",
    "subject": "数A",
    "audience": "文理共通",
    "difficulty": 2,
    "t_number": 190,
    "question_page": 12,
    "answer_page": 180,
    "answer_end_page": 181
  },
  {
    "n": 77,
    "chapter_id": "1.4",
    "chapter_name": "平面図形・空間図形",
    "subject": "数A",
    "audience": "文理共通",
    "difficulty": 2,
    "t_number": 211,
    "question_page": 12,
    "answer_page": 182,
    "answer_end_page": 183
  },
  {
    "n": 78,
    "chapter_id": "1.4",
    "chapter_name": "平面図形・空間図形",
    "subject": "数A",
    "audience": "文理共通",
    "difficulty": 2,
    "t_number": 245,
    "question_page": 12,
    "answer_page": 184,
    "answer_end_page": 185
  },
  {
    "n": 79,
    "chapter_id": "1.4",
    "chapter_name": "平面図形・空間図形",
    "subject": "数A",
    "audience": "文理共通",
    "difficulty": 3,
    "t_number": 2,
    "question_page": 12,
    "answer_page": 186,
    "answer_end_page": 187
  },
  {
    "n": 80,
    "chapter_id": "1.4",
    "chapter_name": "平面図形・空間図形",
    "subject": "数A",
    "audience": "文理共通",
    "difficulty": 3,
    "t_number": 63,
    "question_page": 13,
    "answer_page": 188,
    "answer_end_page": 189
  },
  {
    "n": 81,
    "chapter_id": "1.4",
    "chapter_name": "平面図形・空間図形",
    "subject": "数A",
    "audience": "文理共通",
    "difficulty": 3,
    "t_number": 162,
    "question_page": 13,
    "answer_page": 190,
    "answer_end_page": 191
  },
  {
    "n": 82,
    "chapter_id": "1.4",
    "chapter_name": "平面図形・空間図形",
    "subject": "数A",
    "audience": "文理共通",
    "difficulty": 3,
    "t_number": 188,
    "question_page": 13,
    "answer_page": 192,
    "answer_end_page": 193
  },
  {
    "n": 83,
    "chapter_id": "1.4",
    "chapter_name": "平面図形・空間図形",
    "subject": "数II",
    "audience": "文理共通",
    "difficulty": 2,
    "t_number": 90,
    "question_page": 13,
    "answer_page": 194,
    "answer_end_page": 195
  },
  {
    "n": 84,
    "chapter_id": "1.4",
    "chapter_name": "平面図形・空間図形",
    "subject": "数II",
    "audience": "文理共通",
    "difficulty": 2,
    "t_number": 118,
    "question_page": 13,
    "answer_page": 196,
    "answer_end_page": 197
  },
  {
    "n": 85,
    "chapter_id": "1.4",
    "chapter_name": "平面図形・空間図形",
    "subject": "数II",
    "audience": "文理共通",
    "difficulty": 3,
    "t_number": 96,
    "question_page": 13,
    "answer_page": 198,
    "answer_end_page": 200
  },
  {
    "n": 86,
    "chapter_id": "1.4",
    "chapter_name": "平面図形・空間図形",
    "subject": "数II",
    "audience": "文理共通",
    "difficulty": 3,
    "t_number": 137,
    "question_page": 13,
    "answer_page": 201,
    "answer_end_page": 203
  },
  {
    "n": 87,
    "chapter_id": "1.5",
    "chapter_name": "座標・ベクトル・複素数平面",
    "subject": "数I",
    "audience": "文理共通",
    "difficulty": 1,
    "t_number": 65,
    "question_page": 14,
    "answer_page": 204,
    "answer_end_page": 205
  },
  {
    "n": 88,
    "chapter_id": "1.5",
    "chapter_name": "座標・ベクトル・複素数平面",
    "subject": "数I",
    "audience": "文理共通",
    "difficulty": 1,
    "t_number": 83,
    "question_page": 14,
    "answer_page": 206,
    "answer_end_page": 208
  },
  {
    "n": 89,
    "chapter_id": "1.5",
    "chapter_name": "座標・ベクトル・複素数平面",
    "subject": "数II",
    "audience": "文理共通",
    "difficulty": 1,
    "t_number": 88,
    "question_page": 14,
    "answer_page": 209,
    "answer_end_page": 210
  },
  {
    "n": 90,
    "chapter_id": "1.5",
    "chapter_name": "座標・ベクトル・複素数平面",
    "subject": "数II",
    "audience": "文理共通",
    "difficulty": 1,
    "t_number": 109,
    "question_page": 14,
    "answer_page": 211,
    "answer_end_page": 212
  },
  {
    "n": 91,
    "chapter_id": "1.5",
    "chapter_name": "座標・ベクトル・複素数平面",
    "subject": "数II",
    "audience": "文理共通",
    "difficulty": 1,
    "t_number": 114,
    "question_page": 14,
    "answer_page": 213,
    "answer_end_page": 213
  },
  {
    "n": 92,
    "chapter_id": "1.5",
    "chapter_name": "座標・ベクトル・複素数平面",
    "subject": "数II",
    "audience": "文理共通",
    "difficulty": 1,
    "t_number": 116,
    "question_page": 14,
    "answer_page": 214,
    "answer_end_page": 215
  },
  {
    "n": 93,
    "chapter_id": "1.5",
    "chapter_name": "座標・ベクトル・複素数平面",
    "subject": "数II",
    "audience": "文理共通",
    "difficulty": 1,
    "t_number": 140,
    "question_page": 14,
    "answer_page": 216,
    "answer_end_page": 216
  },
  {
    "n": 94,
    "chapter_id": "1.5",
    "chapter_name": "座標・ベクトル・複素数平面",
    "subject": "数II",
    "audience": "文理共通",
    "difficulty": 1,
    "t_number": 194,
    "question_page": 15,
    "answer_page": 217,
    "answer_end_page": 217
  },
  {
    "n": 95,
    "chapter_id": "1.5",
    "chapter_name": "座標・ベクトル・複素数平面",
    "subject": "数II",
    "audience": "文理共通",
    "difficulty": 1,
    "t_number": 240,
    "question_page": 15,
    "answer_page": 218,
    "answer_end_page": 219
  },
  {
    "n": 96,
    "chapter_id": "1.5",
    "chapter_name": "座標・ベクトル・複素数平面",
    "subject": "数II",
    "audience": "文理共通",
    "difficulty": 2,
    "t_number": 46,
    "question_page": 15,
    "answer_page": 220,
    "answer_end_page": 221
  },
  {
    "n": 97,
    "chapter_id": "1.5",
    "chapter_name": "座標・ベクトル・複素数平面",
    "subject": "数II",
    "audience": "文理共通",
    "difficulty": 2,
    "t_number": 149,
    "question_page": 15,
    "answer_page": 222,
    "answer_end_page": 223
  },
  {
    "n": 98,
    "chapter_id": "1.5",
    "chapter_name": "座標・ベクトル・複素数平面",
    "subject": "数II",
    "audience": "文理共通",
    "difficulty": 2,
    "t_number": 157,
    "question_page": 15,
    "answer_page": 224,
    "answer_end_page": 225
  },
  {
    "n": 99,
    "chapter_id": "1.5",
    "chapter_name": "座標・ベクトル・複素数平面",
    "subject": "数II",
    "audience": "文理共通",
    "difficulty": 2,
    "t_number": 246,
    "question_page": 15,
    "answer_page": 226,
    "answer_end_page": 227
  },
  {
    "n": 100,
    "chapter_id": "1.5",
    "chapter_name": "座標・ベクトル・複素数平面",
    "subject": "数C",
    "audience": "文理共通",
    "difficulty": 1,
    "t_number": 82,
    "question_page": 15,
    "answer_page": 228,
    "answer_end_page": 229
  },
  {
    "n": 101,
    "chapter_id": "1.5",
    "chapter_name": "座標・ベクトル・複素数平面",
    "subject": "数C",
    "audience": "文理共通",
    "difficulty": 1,
    "t_number": 156,
    "question_page": 16,
    "answer_page": 230,
    "answer_end_page": 231
  },
  {
    "n": 102,
    "chapter_id": "1.5",
    "chapter_name": "座標・ベクトル・複素数平面",
    "subject": "数C",
    "audience": "文理共通",
    "difficulty": 1,
    "t_number": 166,
    "question_page": 16,
    "answer_page": 232,
    "answer_end_page": 232
  },
  {
    "n": 103,
    "chapter_id": "1.5",
    "chapter_name": "座標・ベクトル・複素数平面",
    "subject": "数C",
    "audience": "文理共通",
    "difficulty": 1,
    "t_number": 229,
    "question_page": 16,
    "answer_page": 233,
    "answer_end_page": 235
  },
  {
    "n": 104,
    "chapter_id": "1.5",
    "chapter_name": "座標・ベクトル・複素数平面",
    "subject": "数C",
    "audience": "文理共通",
    "difficulty": 1,
    "t_number": 230,
    "question_page": 16,
    "answer_page": 236,
    "answer_end_page": 237
  },
  {
    "n": 105,
    "chapter_id": "1.5",
    "chapter_name": "座標・ベクトル・複素数平面",
    "subject": "数C",
    "audience": "文理共通",
    "difficulty": 2,
    "t_number": 103,
    "question_page": 16,
    "answer_page": 238,
    "answer_end_page": 239
  },
  {
    "n": 106,
    "chapter_id": "1.5",
    "chapter_name": "座標・ベクトル・複素数平面",
    "subject": "数C",
    "audience": "文理共通",
    "difficulty": 2,
    "t_number": 104,
    "question_page": 16,
    "answer_page": 240,
    "answer_end_page": 241
  },
  {
    "n": 107,
    "chapter_id": "1.5",
    "chapter_name": "座標・ベクトル・複素数平面",
    "subject": "数C",
    "audience": "文理共通",
    "difficulty": 2,
    "t_number": 105,
    "question_page": 16,
    "answer_page": 242,
    "answer_end_page": 243
  },
  {
    "n": 108,
    "chapter_id": "1.5",
    "chapter_name": "座標・ベクトル・複素数平面",
    "subject": "数C",
    "audience": "文理共通",
    "difficulty": 2,
    "t_number": 121,
    "question_page": 17,
    "answer_page": 244,
    "answer_end_page": 245
  },
  {
    "n": 109,
    "chapter_id": "1.5",
    "chapter_name": "座標・ベクトル・複素数平面",
    "subject": "数C",
    "audience": "文理共通",
    "difficulty": 2,
    "t_number": 164,
    "question_page": 17,
    "answer_page": 246,
    "answer_end_page": 247
  },
  {
    "n": 110,
    "chapter_id": "1.5",
    "chapter_name": "座標・ベクトル・複素数平面",
    "subject": "数C",
    "audience": "文理共通",
    "difficulty": 3,
    "t_number": 144,
    "question_page": 17,
    "answer_page": 248,
    "answer_end_page": 249
  },
  {
    "n": 111,
    "chapter_id": "1.5",
    "chapter_name": "座標・ベクトル・複素数平面",
    "subject": "数III",
    "audience": "理系のみ",
    "difficulty": 1,
    "t_number": 219,
    "question_page": 17,
    "answer_page": 250,
    "answer_end_page": 251
  },
  {
    "n": 112,
    "chapter_id": "1.5",
    "chapter_name": "座標・ベクトル・複素数平面",
    "subject": "数III",
    "audience": "理系のみ",
    "difficulty": 2,
    "t_number": 218,
    "question_page": 17,
    "answer_page": 252,
    "answer_end_page": 253
  },
  {
    "n": 113,
    "chapter_id": "1.5",
    "chapter_name": "座標・ベクトル・複素数平面",
    "subject": "数III",
    "audience": "理系のみ",
    "difficulty": 2,
    "t_number": 220,
    "question_page": 17,
    "answer_page": 254,
    "answer_end_page": 254
  },
  {
    "n": 114,
    "chapter_id": "1.5",
    "chapter_name": "座標・ベクトル・複素数平面",
    "subject": "数III",
    "audience": "理系のみ",
    "difficulty": 2,
    "t_number": 221,
    "question_page": 17,
    "answer_page": 255,
    "answer_end_page": 256
  },
  {
    "n": 115,
    "chapter_id": "1.5",
    "chapter_name": "座標・ベクトル・複素数平面",
    "subject": "数III",
    "audience": "理系のみ",
    "difficulty": 2,
    "t_number": 223,
    "question_page": 18,
    "answer_page": 257,
    "answer_end_page": 258
  },
  {
    "n": 116,
    "chapter_id": "1.5",
    "chapter_name": "座標・ベクトル・複素数平面",
    "subject": "数III",
    "audience": "理系のみ",
    "difficulty": 2,
    "t_number": 224,
    "question_page": 18,
    "answer_page": 259,
    "answer_end_page": 260
  },
  {
    "n": 117,
    "chapter_id": "1.5",
    "chapter_name": "座標・ベクトル・複素数平面",
    "subject": "数C",
    "audience": "理系のみ",
    "difficulty": 2,
    "t_number": 217,
    "question_page": 18,
    "answer_page": 261,
    "answer_end_page": 262
  },
  {
    "n": 118,
    "chapter_id": "1.6",
    "chapter_name": "整数",
    "subject": "数A",
    "audience": "文理共通",
    "difficulty": 1,
    "t_number": 30,
    "question_page": 18,
    "answer_page": 263,
    "answer_end_page": 264
  },
  {
    "n": 119,
    "chapter_id": "1.6",
    "chapter_name": "整数",
    "subject": "数A",
    "audience": "文理共通",
    "difficulty": 1,
    "t_number": 40,
    "question_page": 18,
    "answer_page": 265,
    "answer_end_page": 265
  },
  {
    "n": 120,
    "chapter_id": "1.6",
    "chapter_name": "整数",
    "subject": "数A",
    "audience": "文理共通",
    "difficulty": 1,
    "t_number": 93,
    "question_page": 18,
    "answer_page": 266,
    "answer_end_page": 267
  },
  {
    "n": 121,
    "chapter_id": "1.6",
    "chapter_name": "整数",
    "subject": "数A",
    "audience": "文理共通",
    "difficulty": 1,
    "t_number": 99,
    "question_page": 18,
    "answer_page": 268,
    "answer_end_page": 268
  },
  {
    "n": 122,
    "chapter_id": "1.6",
    "chapter_name": "整数",
    "subject": "数A",
    "audience": "文理共通",
    "difficulty": 1,
    "t_number": 151,
    "question_page": 19,
    "answer_page": 269,
    "answer_end_page": 270
  },
  {
    "n": 123,
    "chapter_id": "1.6",
    "chapter_name": "整数",
    "subject": "数A",
    "audience": "文理共通",
    "difficulty": 1,
    "t_number": 184,
    "question_page": 19,
    "answer_page": 271,
    "answer_end_page": 271
  },
  {
    "n": 124,
    "chapter_id": "1.6",
    "chapter_name": "整数",
    "subject": "数A",
    "audience": "文理共通",
    "difficulty": 1,
    "t_number": 206,
    "question_page": 19,
    "answer_page": 272,
    "answer_end_page": 273
  },
  {
    "n": 125,
    "chapter_id": "1.6",
    "chapter_name": "整数",
    "subject": "数A",
    "audience": "文理共通",
    "difficulty": 2,
    "t_number": 13,
    "question_page": 19,
    "answer_page": 274,
    "answer_end_page": 275
  },
  {
    "n": 126,
    "chapter_id": "1.6",
    "chapter_name": "整数",
    "subject": "数A",
    "audience": "文理共通",
    "difficulty": 2,
    "t_number": 20,
    "question_page": 19,
    "answer_page": 276,
    "answer_end_page": 276
  },
  {
    "n": 127,
    "chapter_id": "1.6",
    "chapter_name": "整数",
    "subject": "数A",
    "audience": "文理共通",
    "difficulty": 2,
    "t_number": 67,
    "question_page": 19,
    "answer_page": 277,
    "answer_end_page": 278
  },
  {
    "n": 128,
    "chapter_id": "1.6",
    "chapter_name": "整数",
    "subject": "数A",
    "audience": "文理共通",
    "difficulty": 2,
    "t_number": 129,
    "question_page": 19,
    "answer_page": 279,
    "answer_end_page": 280
  },
  {
    "n": 129,
    "chapter_id": "1.6",
    "chapter_name": "整数",
    "subject": "数A",
    "audience": "文理共通",
    "difficulty": 2,
    "t_number": 139,
    "question_page": 19,
    "answer_page": 281,
    "answer_end_page": 282
  },
  {
    "n": 130,
    "chapter_id": "1.6",
    "chapter_name": "整数",
    "subject": "数A",
    "audience": "文理共通",
    "difficulty": 2,
    "t_number": 161,
    "question_page": 20,
    "answer_page": 283,
    "answer_end_page": 283
  },
  {
    "n": 131,
    "chapter_id": "1.6",
    "chapter_name": "整数",
    "subject": "数A",
    "audience": "文理共通",
    "difficulty": 2,
    "t_number": 177,
    "question_page": 20,
    "answer_page": 284,
    "answer_end_page": 285
  },
  {
    "n": 132,
    "chapter_id": "1.6",
    "chapter_name": "整数",
    "subject": "数A",
    "audience": "文理共通",
    "difficulty": 2,
    "t_number": 222,
    "question_page": 20,
    "answer_page": 286,
    "answer_end_page": 286
  },
  {
    "n": 133,
    "chapter_id": "1.6",
    "chapter_name": "整数",
    "subject": "数A",
    "audience": "文理共通",
    "difficulty": 2,
    "t_number": 231,
    "question_page": 20,
    "answer_page": 287,
    "answer_end_page": 288
  },
  {
    "n": 134,
    "chapter_id": "1.6",
    "chapter_name": "整数",
    "subject": "数A",
    "audience": "文理共通",
    "difficulty": 3,
    "t_number": 54,
    "question_page": 20,
    "answer_page": 289,
    "answer_end_page": 289
  },
  {
    "n": 135,
    "chapter_id": "1.6",
    "chapter_name": "整数",
    "subject": "数A",
    "audience": "文理共通",
    "difficulty": 3,
    "t_number": 111,
    "question_page": 20,
    "answer_page": 290,
    "answer_end_page": 291
  },
  {
    "n": 136,
    "chapter_id": "1.6",
    "chapter_name": "整数",
    "subject": "数A",
    "audience": "文理共通",
    "difficulty": 3,
    "t_number": 146,
    "question_page": 20,
    "answer_page": 292,
    "answer_end_page": 292
  },
  {
    "n": 137,
    "chapter_id": "1.6",
    "chapter_name": "整数",
    "subject": "数A",
    "audience": "文理共通",
    "difficulty": 3,
    "t_number": 158,
    "question_page": 20,
    "answer_page": 293,
    "answer_end_page": 293
  },
  {
    "n": 138,
    "chapter_id": "1.6",
    "chapter_name": "整数",
    "subject": "数A",
    "audience": "文理共通",
    "difficulty": 3,
    "t_number": 239,
    "question_page": 21,
    "answer_page": 294,
    "answer_end_page": 295
  },
  {
    "n": 139,
    "chapter_id": "1.7",
    "chapter_name": "場合の数・確率",
    "subject": "数A",
    "audience": "文理共通",
    "difficulty": 1,
    "t_number": 59,
    "question_page": 21,
    "answer_page": 296,
    "answer_end_page": 297
  },
  {
    "n": 140,
    "chapter_id": "1.7",
    "chapter_name": "場合の数・確率",
    "subject": "数A",
    "audience": "文理共通",
    "difficulty": 1,
    "t_number": 107,
    "question_page": 21,
    "answer_page": 298,
    "answer_end_page": 299
  },
  {
    "n": 141,
    "chapter_id": "1.7",
    "chapter_name": "場合の数・確率",
    "subject": "数A",
    "audience": "文理共通",
    "difficulty": 1,
    "t_number": 155,
    "question_page": 21,
    "answer_page": 300,
    "answer_end_page": 300
  },
  {
    "n": 142,
    "chapter_id": "1.7",
    "chapter_name": "場合の数・確率",
    "subject": "数A",
    "audience": "文理共通",
    "difficulty": 1,
    "t_number": 170,
    "question_page": 21,
    "answer_page": 301,
    "answer_end_page": 301
  },
  {
    "n": 143,
    "chapter_id": "1.7",
    "chapter_name": "場合の数・確率",
    "subject": "数A",
    "audience": "文理共通",
    "difficulty": 1,
    "t_number": 173,
    "question_page": 21,
    "answer_page": 302,
    "answer_end_page": 302
  },
  {
    "n": 144,
    "chapter_id": "1.7",
    "chapter_name": "場合の数・確率",
    "subject": "数A",
    "audience": "文理共通",
    "difficulty": 2,
    "t_number": 12,
    "question_page": 21,
    "answer_page": 303,
    "answer_end_page": 303
  },
  {
    "n": 145,
    "chapter_id": "1.7",
    "chapter_name": "場合の数・確率",
    "subject": "数A",
    "audience": "文理共通",
    "difficulty": 2,
    "t_number": 18,
    "question_page": 22,
    "answer_page": 304,
    "answer_end_page": 304
  },
  {
    "n": 146,
    "chapter_id": "1.7",
    "chapter_name": "場合の数・確率",
    "subject": "数A",
    "audience": "文理共通",
    "difficulty": 2,
    "t_number": 48,
    "question_page": 22,
    "answer_page": 305,
    "answer_end_page": 306
  },
  {
    "n": 147,
    "chapter_id": "1.7",
    "chapter_name": "場合の数・確率",
    "subject": "数A",
    "audience": "文理共通",
    "difficulty": 2,
    "t_number": 50,
    "question_page": 22,
    "answer_page": 307,
    "answer_end_page": 308
  },
  {
    "n": 148,
    "chapter_id": "1.7",
    "chapter_name": "場合の数・確率",
    "subject": "数A",
    "audience": "文理共通",
    "difficulty": 2,
    "t_number": 61,
    "question_page": 22,
    "answer_page": 309,
    "answer_end_page": 310
  },
  {
    "n": 149,
    "chapter_id": "1.7",
    "chapter_name": "場合の数・確率",
    "subject": "数A",
    "audience": "文理共通",
    "difficulty": 2,
    "t_number": 101,
    "question_page": 22,
    "answer_page": 311,
    "answer_end_page": 311
  },
  {
    "n": 150,
    "chapter_id": "1.7",
    "chapter_name": "場合の数・確率",
    "subject": "数A",
    "audience": "文理共通",
    "difficulty": 2,
    "t_number": 110,
    "question_page": 22,
    "answer_page": 312,
    "answer_end_page": 312
  },
  {
    "n": 151,
    "chapter_id": "1.7",
    "chapter_name": "場合の数・確率",
    "subject": "数A",
    "audience": "文理共通",
    "difficulty": 2,
    "t_number": 120,
    "question_page": 22,
    "answer_page": 313,
    "answer_end_page": 314
  },
  {
    "n": 152,
    "chapter_id": "1.7",
    "chapter_name": "場合の数・確率",
    "subject": "数A",
    "audience": "文理共通",
    "difficulty": 2,
    "t_number": 153,
    "question_page": 23,
    "answer_page": 315,
    "answer_end_page": 315
  },
  {
    "n": 153,
    "chapter_id": "1.7",
    "chapter_name": "場合の数・確率",
    "subject": "数A",
    "audience": "文理共通",
    "difficulty": 2,
    "t_number": 163,
    "question_page": 23,
    "answer_page": 316,
    "answer_end_page": 316
  },
  {
    "n": 154,
    "chapter_id": "1.7",
    "chapter_name": "場合の数・確率",
    "subject": "数A",
    "audience": "文理共通",
    "difficulty": 2,
    "t_number": 209,
    "question_page": 23,
    "answer_page": 317,
    "answer_end_page": 318
  },
  {
    "n": 155,
    "chapter_id": "1.7",
    "chapter_name": "場合の数・確率",
    "subject": "数A",
    "audience": "文理共通",
    "difficulty": 2,
    "t_number": 237,
    "question_page": 23,
    "answer_page": 319,
    "answer_end_page": 320
  },
  {
    "n": 156,
    "chapter_id": "1.7",
    "chapter_name": "場合の数・確率",
    "subject": "数A",
    "audience": "文理共通",
    "difficulty": 2,
    "t_number": 244,
    "question_page": 23,
    "answer_page": 321,
    "answer_end_page": 322
  },
  {
    "n": 157,
    "chapter_id": "1.7",
    "chapter_name": "場合の数・確率",
    "subject": "数A",
    "audience": "文理共通",
    "difficulty": 3,
    "t_number": 226,
    "question_page": 23,
    "answer_page": 323,
    "answer_end_page": 324
  },
  {
    "n": 158,
    "chapter_id": "1.7",
    "chapter_name": "場合の数・確率",
    "subject": "数B",
    "audience": "文理共通",
    "difficulty": 2,
    "t_number": 179,
    "question_page": 24,
    "answer_page": 325,
    "answer_end_page": 326
  },
  {
    "n": 159,
    "chapter_id": "1.7",
    "chapter_name": "場合の数・確率",
    "subject": "数III",
    "audience": "理系のみ",
    "difficulty": 2,
    "t_number": 127,
    "question_page": 24,
    "answer_page": 327,
    "answer_end_page": 328
  },
  {
    "n": 160,
    "chapter_id": "1.8",
    "chapter_name": "数列・漸化式",
    "subject": "数A",
    "audience": "文理共通",
    "difficulty": 1,
    "t_number": 208,
    "question_page": 24,
    "answer_page": 329,
    "answer_end_page": 329
  },
  {
    "n": 161,
    "chapter_id": "1.8",
    "chapter_name": "数列・漸化式",
    "subject": "数B",
    "audience": "文理共通",
    "difficulty": 1,
    "t_number": 56,
    "question_page": 24,
    "answer_page": 330,
    "answer_end_page": 331
  },
  {
    "n": 162,
    "chapter_id": "1.8",
    "chapter_name": "数列・漸化式",
    "subject": "数B",
    "audience": "文理共通",
    "difficulty": 1,
    "t_number": 97,
    "question_page": 24,
    "answer_page": 332,
    "answer_end_page": 333
  },
  {
    "n": 163,
    "chapter_id": "1.8",
    "chapter_name": "数列・漸化式",
    "subject": "数B",
    "audience": "文理共通",
    "difficulty": 1,
    "t_number": 108,
    "question_page": 24,
    "answer_page": 334,
    "answer_end_page": 334
  },
  {
    "n": 164,
    "chapter_id": "1.8",
    "chapter_name": "数列・漸化式",
    "subject": "数B",
    "audience": "文理共通",
    "difficulty": 1,
    "t_number": 115,
    "question_page": 25,
    "answer_page": 335,
    "answer_end_page": 336
  },
  {
    "n": 165,
    "chapter_id": "1.8",
    "chapter_name": "数列・漸化式",
    "subject": "数B",
    "audience": "文理共通",
    "difficulty": 1,
    "t_number": 143,
    "question_page": 25,
    "answer_page": 337,
    "answer_end_page": 338
  },
  {
    "n": 166,
    "chapter_id": "1.8",
    "chapter_name": "数列・漸化式",
    "subject": "数B",
    "audience": "文理共通",
    "difficulty": 2,
    "t_number": 16,
    "question_page": 25,
    "answer_page": 339,
    "answer_end_page": 340
  },
  {
    "n": 167,
    "chapter_id": "1.8",
    "chapter_name": "数列・漸化式",
    "subject": "数B",
    "audience": "文理共通",
    "difficulty": 2,
    "t_number": 39,
    "question_page": 25,
    "answer_page": 341,
    "answer_end_page": 341
  },
  {
    "n": 168,
    "chapter_id": "1.8",
    "chapter_name": "数列・漸化式",
    "subject": "数B",
    "audience": "文理共通",
    "difficulty": 2,
    "t_number": 169,
    "question_page": 25,
    "answer_page": 342,
    "answer_end_page": 343
  },
  {
    "n": 169,
    "chapter_id": "1.8",
    "chapter_name": "数列・漸化式",
    "subject": "数B",
    "audience": "文理共通",
    "difficulty": 2,
    "t_number": 192,
    "question_page": 25,
    "answer_page": 344,
    "answer_end_page": 344
  },
  {
    "n": 170,
    "chapter_id": "1.8",
    "chapter_name": "数列・漸化式",
    "subject": "数B",
    "audience": "文理共通",
    "difficulty": 2,
    "t_number": 210,
    "question_page": 25,
    "answer_page": 345,
    "answer_end_page": 346
  },
  {
    "n": 171,
    "chapter_id": "1.8",
    "chapter_name": "数列・漸化式",
    "subject": "数B",
    "audience": "文理共通",
    "difficulty": 2,
    "t_number": 241,
    "question_page": 26,
    "answer_page": 347,
    "answer_end_page": 348
  },
  {
    "n": 172,
    "chapter_id": "1.8",
    "chapter_name": "数列・漸化式",
    "subject": "数B",
    "audience": "文理共通",
    "difficulty": 3,
    "t_number": 1,
    "question_page": 26,
    "answer_page": 349,
    "answer_end_page": 349
  },
  {
    "n": 173,
    "chapter_id": "1.8",
    "chapter_name": "数列・漸化式",
    "subject": "数B",
    "audience": "文理共通",
    "difficulty": 3,
    "t_number": 68,
    "question_page": 26,
    "answer_page": 350,
    "answer_end_page": 351
  },
  {
    "n": 174,
    "chapter_id": "1.8",
    "chapter_name": "数列・漸化式",
    "subject": "数III",
    "audience": "理系のみ",
    "difficulty": 2,
    "t_number": 191,
    "question_page": 26,
    "answer_page": 352,
    "answer_end_page": 353
  },
  {
    "n": 175,
    "chapter_id": "1.9",
    "chapter_name": "三角関数・指数・対数",
    "subject": "数I",
    "audience": "文理共通",
    "difficulty": 1,
    "t_number": 176,
    "question_page": 26,
    "answer_page": 354,
    "answer_end_page": 355
  },
  {
    "n": 176,
    "chapter_id": "1.9",
    "chapter_name": "三角関数・指数・対数",
    "subject": "数II",
    "audience": "文理共通",
    "difficulty": 1,
    "t_number": 11,
    "question_page": 26,
    "answer_page": 356,
    "answer_end_page": 357
  },
  {
    "n": 177,
    "chapter_id": "1.9",
    "chapter_name": "三角関数・指数・対数",
    "subject": "数II",
    "audience": "文理共通",
    "difficulty": 1,
    "t_number": 19,
    "question_page": 26,
    "answer_page": 358,
    "answer_end_page": 359
  },
  {
    "n": 178,
    "chapter_id": "1.9",
    "chapter_name": "三角関数・指数・対数",
    "subject": "数II",
    "audience": "文理共通",
    "difficulty": 1,
    "t_number": 27,
    "question_page": 27,
    "answer_page": 360,
    "answer_end_page": 360
  },
  {
    "n": 179,
    "chapter_id": "1.9",
    "chapter_name": "三角関数・指数・対数",
    "subject": "数II",
    "audience": "文理共通",
    "difficulty": 1,
    "t_number": 62,
    "question_page": 27,
    "answer_page": 361,
    "answer_end_page": 362
  },
  {
    "n": 180,
    "chapter_id": "1.9",
    "chapter_name": "三角関数・指数・対数",
    "subject": "数II",
    "audience": "文理共通",
    "difficulty": 1,
    "t_number": 125,
    "question_page": 27,
    "answer_page": 363,
    "answer_end_page": 364
  },
  {
    "n": 181,
    "chapter_id": "1.9",
    "chapter_name": "三角関数・指数・対数",
    "subject": "数II",
    "audience": "文理共通",
    "difficulty": 1,
    "t_number": 142,
    "question_page": 27,
    "answer_page": 365,
    "answer_end_page": 365
  },
  {
    "n": 182,
    "chapter_id": "1.9",
    "chapter_name": "三角関数・指数・対数",
    "subject": "数II",
    "audience": "文理共通",
    "difficulty": 1,
    "t_number": 147,
    "question_page": 27,
    "answer_page": 366,
    "answer_end_page": 367
  },
  {
    "n": 183,
    "chapter_id": "1.9",
    "chapter_name": "三角関数・指数・対数",
    "subject": "数II",
    "audience": "文理共通",
    "difficulty": 1,
    "t_number": 148,
    "question_page": 27,
    "answer_page": 368,
    "answer_end_page": 368
  },
  {
    "n": 184,
    "chapter_id": "1.9",
    "chapter_name": "三角関数・指数・対数",
    "subject": "数II",
    "audience": "文理共通",
    "difficulty": 1,
    "t_number": 203,
    "question_page": 27,
    "answer_page": 369,
    "answer_end_page": 369
  },
  {
    "n": 185,
    "chapter_id": "1.9",
    "chapter_name": "三角関数・指数・対数",
    "subject": "数II",
    "audience": "文理共通",
    "difficulty": 1,
    "t_number": 213,
    "question_page": 28,
    "answer_page": 370,
    "answer_end_page": 371
  },
  {
    "n": 186,
    "chapter_id": "1.9",
    "chapter_name": "三角関数・指数・対数",
    "subject": "数II",
    "audience": "文理共通",
    "difficulty": 2,
    "t_number": 126,
    "question_page": 28,
    "answer_page": 372,
    "answer_end_page": 372
  },
  {
    "n": 187,
    "chapter_id": "1.9",
    "chapter_name": "三角関数・指数・対数",
    "subject": "数II",
    "audience": "文理共通",
    "difficulty": 2,
    "t_number": 242,
    "question_page": 28,
    "answer_page": 373,
    "answer_end_page": 374
  },
  {
    "n": 188,
    "chapter_id": "1.9",
    "chapter_name": "三角関数・指数・対数",
    "subject": "数II",
    "audience": "文理共通",
    "difficulty": 3,
    "t_number": 3,
    "question_page": 28,
    "answer_page": 375,
    "answer_end_page": 375
  },
  {
    "n": 189,
    "chapter_id": "1.9",
    "chapter_name": "三角関数・指数・対数",
    "subject": "数II",
    "audience": "文理共通",
    "difficulty": 3,
    "t_number": 57,
    "question_page": 28,
    "answer_page": 376,
    "answer_end_page": 377
  },
  {
    "n": 190,
    "chapter_id": "1.9",
    "chapter_name": "三角関数・指数・対数",
    "subject": "数II",
    "audience": "文理共通",
    "difficulty": 3,
    "t_number": 78,
    "question_page": 28,
    "answer_page": 378,
    "answer_end_page": 379
  },
  {
    "n": 191,
    "chapter_id": "1.9",
    "chapter_name": "三角関数・指数・対数",
    "subject": "数II",
    "audience": "文理共通",
    "difficulty": 3,
    "t_number": 86,
    "question_page": 28,
    "answer_page": 380,
    "answer_end_page": 381
  },
  {
    "n": 192,
    "chapter_id": "1.9",
    "chapter_name": "三角関数・指数・対数",
    "subject": "数II",
    "audience": "文理共通",
    "difficulty": 3,
    "t_number": 141,
    "question_page": 28,
    "answer_page": 382,
    "answer_end_page": 383
  },
  {
    "n": 193,
    "chapter_id": "1.9",
    "chapter_name": "三角関数・指数・対数",
    "subject": "数II",
    "audience": "文理共通",
    "difficulty": 3,
    "t_number": 185,
    "question_page": 29,
    "answer_page": 384,
    "answer_end_page": 386
  },
  {
    "n": 194,
    "chapter_id": "1.9",
    "chapter_name": "三角関数・指数・対数",
    "subject": "数III",
    "audience": "理系のみ",
    "difficulty": 1,
    "t_number": 212,
    "question_page": 29,
    "answer_page": 387,
    "answer_end_page": 388
  },
  {
    "n": 195,
    "chapter_id": "1.10",
    "chapter_name": "極限・微分",
    "subject": "数II",
    "audience": "文理共通",
    "difficulty": 1,
    "t_number": 77,
    "question_page": 29,
    "answer_page": 389,
    "answer_end_page": 390
  },
  {
    "n": 196,
    "chapter_id": "1.10",
    "chapter_name": "極限・微分",
    "subject": "数III",
    "audience": "理系のみ",
    "difficulty": 1,
    "t_number": 8,
    "question_page": 29,
    "answer_page": 391,
    "answer_end_page": 391
  },
  {
    "n": 197,
    "chapter_id": "1.10",
    "chapter_name": "極限・微分",
    "subject": "数III",
    "audience": "理系のみ",
    "difficulty": 1,
    "t_number": 49,
    "question_page": 29,
    "answer_page": 392,
    "answer_end_page": 392
  },
  {
    "n": 198,
    "chapter_id": "1.10",
    "chapter_name": "極限・微分",
    "subject": "数III",
    "audience": "理系のみ",
    "difficulty": 1,
    "t_number": 52,
    "question_page": 29,
    "answer_page": 393,
    "answer_end_page": 394
  },
  {
    "n": 199,
    "chapter_id": "1.10",
    "chapter_name": "極限・微分",
    "subject": "数III",
    "audience": "理系のみ",
    "difficulty": 1,
    "t_number": 85,
    "question_page": 29,
    "answer_page": 395,
    "answer_end_page": 396
  },
  {
    "n": 200,
    "chapter_id": "1.10",
    "chapter_name": "極限・微分",
    "subject": "数III",
    "audience": "理系のみ",
    "difficulty": 1,
    "t_number": 89,
    "question_page": 30,
    "answer_page": 397,
    "answer_end_page": 398
  },
  {
    "n": 201,
    "chapter_id": "1.10",
    "chapter_name": "極限・微分",
    "subject": "数III",
    "audience": "理系のみ",
    "difficulty": 1,
    "t_number": 91,
    "question_page": 30,
    "answer_page": 399,
    "answer_end_page": 400
  },
  {
    "n": 202,
    "chapter_id": "1.10",
    "chapter_name": "極限・微分",
    "subject": "数III",
    "audience": "理系のみ",
    "difficulty": 1,
    "t_number": 119,
    "question_page": 30,
    "answer_page": 401,
    "answer_end_page": 402
  },
  {
    "n": 203,
    "chapter_id": "1.10",
    "chapter_name": "極限・微分",
    "subject": "数III",
    "audience": "理系のみ",
    "difficulty": 1,
    "t_number": 132,
    "question_page": 30,
    "answer_page": 403,
    "answer_end_page": 403
  },
  {
    "n": 204,
    "chapter_id": "1.10",
    "chapter_name": "極限・微分",
    "subject": "数III",
    "audience": "理系のみ",
    "difficulty": 1,
    "t_number": 150,
    "question_page": 30,
    "answer_page": 404,
    "answer_end_page": 405
  },
  {
    "n": 205,
    "chapter_id": "1.10",
    "chapter_name": "極限・微分",
    "subject": "数III",
    "audience": "理系のみ",
    "difficulty": 1,
    "t_number": 160,
    "question_page": 30,
    "answer_page": 406,
    "answer_end_page": 406
  },
  {
    "n": 206,
    "chapter_id": "1.10",
    "chapter_name": "極限・微分",
    "subject": "数III",
    "audience": "理系のみ",
    "difficulty": 1,
    "t_number": 180,
    "question_page": 30,
    "answer_page": 407,
    "answer_end_page": 408
  },
  {
    "n": 207,
    "chapter_id": "1.10",
    "chapter_name": "極限・微分",
    "subject": "数III",
    "audience": "理系のみ",
    "difficulty": 1,
    "t_number": 227,
    "question_page": 30,
    "answer_page": 409,
    "answer_end_page": 410
  },
  {
    "n": 208,
    "chapter_id": "1.10",
    "chapter_name": "極限・微分",
    "subject": "数III",
    "audience": "理系のみ",
    "difficulty": 1,
    "t_number": 248,
    "question_page": 31,
    "answer_page": 411,
    "answer_end_page": 411
  },
  {
    "n": 209,
    "chapter_id": "1.10",
    "chapter_name": "極限・微分",
    "subject": "数III",
    "audience": "理系のみ",
    "difficulty": 2,
    "t_number": 10,
    "question_page": 31,
    "answer_page": 412,
    "answer_end_page": 412
  },
  {
    "n": 210,
    "chapter_id": "1.10",
    "chapter_name": "極限・微分",
    "subject": "数III",
    "audience": "理系のみ",
    "difficulty": 2,
    "t_number": 43,
    "question_page": 31,
    "answer_page": 413,
    "answer_end_page": 414
  },
  {
    "n": 211,
    "chapter_id": "1.10",
    "chapter_name": "極限・微分",
    "subject": "数III",
    "audience": "理系のみ",
    "difficulty": 2,
    "t_number": 79,
    "question_page": 31,
    "answer_page": 415,
    "answer_end_page": 416
  },
  {
    "n": 212,
    "chapter_id": "1.10",
    "chapter_name": "極限・微分",
    "subject": "数III",
    "audience": "理系のみ",
    "difficulty": 2,
    "t_number": 168,
    "question_page": 31,
    "answer_page": 417,
    "answer_end_page": 418
  },
  {
    "n": 213,
    "chapter_id": "1.10",
    "chapter_name": "極限・微分",
    "subject": "数III",
    "audience": "理系のみ",
    "difficulty": 2,
    "t_number": 174,
    "question_page": 31,
    "answer_page": 419,
    "answer_end_page": 420
  },
  {
    "n": 214,
    "chapter_id": "1.10",
    "chapter_name": "極限・微分",
    "subject": "数III",
    "audience": "理系のみ",
    "difficulty": 2,
    "t_number": 187,
    "question_page": 31,
    "answer_page": 421,
    "answer_end_page": 422
  },
  {
    "n": 215,
    "chapter_id": "1.10",
    "chapter_name": "極限・微分",
    "subject": "数III",
    "audience": "理系のみ",
    "difficulty": 2,
    "t_number": 195,
    "question_page": 32,
    "answer_page": 423,
    "answer_end_page": 424
  },
  {
    "n": 216,
    "chapter_id": "1.10",
    "chapter_name": "極限・微分",
    "subject": "数III",
    "audience": "理系のみ",
    "difficulty": 2,
    "t_number": 225,
    "question_page": 32,
    "answer_page": 425,
    "answer_end_page": 427
  },
  {
    "n": 217,
    "chapter_id": "1.10",
    "chapter_name": "極限・微分",
    "subject": "数III",
    "audience": "理系のみ",
    "difficulty": 3,
    "t_number": 75,
    "question_page": 32,
    "answer_page": 428,
    "answer_end_page": 429
  },
  {
    "n": 218,
    "chapter_id": "1.11",
    "chapter_name": "積分",
    "subject": "数II",
    "audience": "文理共通",
    "difficulty": 1,
    "t_number": 154,
    "question_page": 32,
    "answer_page": 430,
    "answer_end_page": 431
  },
  {
    "n": 219,
    "chapter_id": "1.11",
    "chapter_name": "積分",
    "subject": "数II",
    "audience": "文理共通",
    "difficulty": 2,
    "t_number": 21,
    "question_page": 32,
    "answer_page": 432,
    "answer_end_page": 433
  },
  {
    "n": 220,
    "chapter_id": "1.11",
    "chapter_name": "積分",
    "subject": "数II",
    "audience": "文理共通",
    "difficulty": 2,
    "t_number": 117,
    "question_page": 32,
    "answer_page": 434,
    "answer_end_page": 435
  },
  {
    "n": 221,
    "chapter_id": "1.11",
    "chapter_name": "積分",
    "subject": "数II",
    "audience": "文理共通",
    "difficulty": 2,
    "t_number": 193,
    "question_page": 32,
    "answer_page": 436,
    "answer_end_page": 437
  },
  {
    "n": 222,
    "chapter_id": "1.11",
    "chapter_name": "積分",
    "subject": "数II",
    "audience": "文理共通",
    "difficulty": 2,
    "t_number": 247,
    "question_page": 33,
    "answer_page": 438,
    "answer_end_page": 439
  },
  {
    "n": 223,
    "chapter_id": "1.11",
    "chapter_name": "積分",
    "subject": "数II",
    "audience": "文理共通",
    "difficulty": 3,
    "t_number": 55,
    "question_page": 33,
    "answer_page": 440,
    "answer_end_page": 441
  },
  {
    "n": 224,
    "chapter_id": "1.11",
    "chapter_name": "積分",
    "subject": "数II",
    "audience": "文理共通",
    "difficulty": 3,
    "t_number": 131,
    "question_page": 33,
    "answer_page": 442,
    "answer_end_page": 443
  },
  {
    "n": 225,
    "chapter_id": "1.11",
    "chapter_name": "積分",
    "subject": "数III",
    "audience": "理系のみ",
    "difficulty": 1,
    "t_number": 29,
    "question_page": 33,
    "answer_page": 444,
    "answer_end_page": 445
  },
  {
    "n": 226,
    "chapter_id": "1.11",
    "chapter_name": "積分",
    "subject": "数III",
    "audience": "理系のみ",
    "difficulty": 1,
    "t_number": 34,
    "question_page": 33,
    "answer_page": 446,
    "answer_end_page": 446
  },
  {
    "n": 227,
    "chapter_id": "1.11",
    "chapter_name": "積分",
    "subject": "数III",
    "audience": "理系のみ",
    "difficulty": 1,
    "t_number": 70,
    "question_page": 33,
    "answer_page": 447,
    "answer_end_page": 447
  },
  {
    "n": 228,
    "chapter_id": "1.11",
    "chapter_name": "積分",
    "subject": "数III",
    "audience": "理系のみ",
    "difficulty": 1,
    "t_number": 84,
    "question_page": 33,
    "answer_page": 448,
    "answer_end_page": 449
  },
  {
    "n": 229,
    "chapter_id": "1.11",
    "chapter_name": "積分",
    "subject": "数III",
    "audience": "理系のみ",
    "difficulty": 2,
    "t_number": 4,
    "question_page": 34,
    "answer_page": 450,
    "answer_end_page": 451
  },
  {
    "n": 230,
    "chapter_id": "1.11",
    "chapter_name": "積分",
    "subject": "数III",
    "audience": "理系のみ",
    "difficulty": 2,
    "t_number": 7,
    "question_page": 34,
    "answer_page": 452,
    "answer_end_page": 453
  },
  {
    "n": 231,
    "chapter_id": "1.11",
    "chapter_name": "積分",
    "subject": "数III",
    "audience": "理系のみ",
    "difficulty": 2,
    "t_number": 24,
    "question_page": 34,
    "answer_page": 454,
    "answer_end_page": 455
  },
  {
    "n": 232,
    "chapter_id": "1.11",
    "chapter_name": "積分",
    "subject": "数III",
    "audience": "理系のみ",
    "difficulty": 2,
    "t_number": 38,
    "question_page": 34,
    "answer_page": 456,
    "answer_end_page": 457
  },
  {
    "n": 233,
    "chapter_id": "1.11",
    "chapter_name": "積分",
    "subject": "数III",
    "audience": "理系のみ",
    "difficulty": 2,
    "t_number": 106,
    "question_page": 34,
    "answer_page": 458,
    "answer_end_page": 459
  },
  {
    "n": 234,
    "chapter_id": "1.11",
    "chapter_name": "積分",
    "subject": "数III",
    "audience": "理系のみ",
    "difficulty": 2,
    "t_number": 135,
    "question_page": 34,
    "answer_page": 460,
    "answer_end_page": 461
  },
  {
    "n": 235,
    "chapter_id": "1.11",
    "chapter_name": "積分",
    "subject": "数III",
    "audience": "理系のみ",
    "difficulty": 2,
    "t_number": 182,
    "question_page": 34,
    "answer_page": 462,
    "answer_end_page": 463
  },
  {
    "n": 236,
    "chapter_id": "1.11",
    "chapter_name": "積分",
    "subject": "数III",
    "audience": "理系のみ",
    "difficulty": 2,
    "t_number": 189,
    "question_page": 35,
    "answer_page": 464,
    "answer_end_page": 465
  },
  {
    "n": 237,
    "chapter_id": "1.11",
    "chapter_name": "積分",
    "subject": "数III",
    "audience": "理系のみ",
    "difficulty": 2,
    "t_number": 199,
    "question_page": 35,
    "answer_page": 466,
    "answer_end_page": 467
  },
  {
    "n": 238,
    "chapter_id": "1.11",
    "chapter_name": "積分",
    "subject": "数III",
    "audience": "理系のみ",
    "difficulty": 3,
    "t_number": 25,
    "question_page": 35,
    "answer_page": 468,
    "answer_end_page": 469
  },
  {
    "n": 239,
    "chapter_id": "1.11",
    "chapter_name": "積分",
    "subject": "数III",
    "audience": "理系のみ",
    "difficulty": 3,
    "t_number": 112,
    "question_page": 35,
    "answer_page": 470,
    "answer_end_page": 471
  },
  {
    "n": 240,
    "chapter_id": "1.11",
    "chapter_name": "積分",
    "subject": "数III",
    "audience": "理系のみ",
    "difficulty": 3,
    "t_number": 198,
    "question_page": 35,
    "answer_page": 472,
    "answer_end_page": 473
  },
  {
    "n": 241,
    "chapter_id": "1.11",
    "chapter_name": "積分",
    "subject": "数C",
    "audience": "理系のみ",
    "difficulty": 3,
    "t_number": 186,
    "question_page": 35,
    "answer_page": 474,
    "answer_end_page": 475
  },
  {
    "n": 242,
    "chapter_id": "1.12",
    "chapter_name": "データの分析・その他",
    "subject": "数I",
    "audience": "文理共通",
    "difficulty": 1,
    "t_number": 73,
    "question_page": 35,
    "answer_page": 476,
    "answer_end_page": 477
  },
  {
    "n": 243,
    "chapter_id": "1.12",
    "chapter_name": "データの分析・その他",
    "subject": "数I",
    "audience": "文理共通",
    "difficulty": 1,
    "t_number": 214,
    "question_page": 36,
    "answer_page": 478,
    "answer_end_page": 478
  },
  {
    "n": 244,
    "chapter_id": "1.12",
    "chapter_name": "データの分析・その他",
    "subject": "数I",
    "audience": "文理共通",
    "difficulty": 1,
    "t_number": 215,
    "question_page": 36,
    "answer_page": 479,
    "answer_end_page": 479
  },
  {
    "n": 245,
    "chapter_id": "1.12",
    "chapter_name": "データの分析・その他",
    "subject": "数I",
    "audience": "文理共通",
    "difficulty": 2,
    "t_number": 216,
    "question_page": 36,
    "answer_page": 480,
    "answer_end_page": 481
  },
  {
    "n": 246,
    "chapter_id": "1.12",
    "chapter_name": "データの分析・その他",
    "subject": "数C",
    "audience": "文理共通",
    "difficulty": 1,
    "t_number": 32,
    "question_page": 36,
    "answer_page": 482,
    "answer_end_page": 483
  },
  {
    "n": 247,
    "chapter_id": "1.12",
    "chapter_name": "データの分析・その他",
    "subject": "数C",
    "audience": "文理共通",
    "difficulty": 1,
    "t_number": 205,
    "question_page": 36,
    "answer_page": 484,
    "answer_end_page": 485
  },
  {
    "n": 248,
    "chapter_id": "1.12",
    "chapter_name": "データの分析・その他",
    "subject": "数III",
    "audience": "理系のみ",
    "difficulty": 3,
    "t_number": 249,
    "question_page": 36,
    "answer_page": 486,
    "answer_end_page": 487
  },
  {
    "n": 249,
    "chapter_id": "1.12",
    "chapter_name": "データの分析・その他",
    "subject": "数C",
    "audience": "理系のみ",
    "difficulty": 2,
    "t_number": 98,
    "question_page": 36,
    "answer_page": 488,
    "answer_end_page": 489
  },
  {
    "n": 250,
    "chapter_id": "1.12",
    "chapter_name": "データの分析・その他",
    "subject": "数C",
    "audience": "理系のみ",
    "difficulty": 3,
    "t_number": 17,
    "question_page": 36,
    "answer_page": 490,
    "answer_end_page": 491
  }
]